infi.ramen_client-1.40.post3-py2.7-nspkg.pth
infi/ramen_client/__init__.py
infi/ramen_client/__version__.py
infi/ramen_client/config.py
infi/ramen_client/queue.py
infi/ramen_client/queue_reader.py
infi/ramen_client/queue_writer.py
infi/ramen_client/utils.py
infi.ramen_client-1.40.post3.dist-info/DESCRIPTION.rst
infi.ramen_client-1.40.post3.dist-info/METADATA
infi.ramen_client-1.40.post3.dist-info/RECORD
infi.ramen_client-1.40.post3.dist-info/WHEEL
infi.ramen_client-1.40.post3.dist-info/entry_points.txt
infi.ramen_client-1.40.post3.dist-info/metadata.json
infi.ramen_client-1.40.post3.dist-info/namespace_packages.txt
infi.ramen_client-1.40.post3.dist-info/top_level.txt
tests/__init__.py
tests/mock_server.py
tests/test_blacklist.py
tests/test_config.py
tests/test_queue_reader.py
tests/test_queue_writer.py
